dedsec_cli/__init__.py
dedsec_cli/dedsec_cli.py
dedsec_cli/sample.py
dedsec_cli-1.0.dist-info/METADATA
dedsec_cli-1.0.dist-info/WHEEL
dedsec_cli-1.0.dist-info/top_level.txt
dedsec_cli-1.0.dist-info/RECORD
