Metadata-Version: 2.4
Name: dedsec_cli
Version: 1.0
Summary: Dedsec UI helpers for Python CLIs
Home-page: https://github.com/0xbitx/dedsec_cli_utils
Author: 0xbit
Classifier: Programming Language :: Python :: 3
Requires-Python: >=3.7
Requires-Dist: pyfiglet
Dynamic: author
Dynamic: classifier
Dynamic: home-page
Dynamic: requires-dist
Dynamic: requires-python
Dynamic: summary
